[
  {
    "id": "main-quests",
    "label": "Main Wishes",
    "desc": "Complete all main storyline quests in Pharloom.",
    "contrib": 0,
    "items": [
      {
        "id": "citadel-seeker",
        "label": "The Great Citadel",
        "type": "quest",
        "flag": "Citadel Seeker",
        "icon": "assets/quest/Seek_Quest_Icon.png",
        "description": "Ascend through the lands of Pharloom and reach the Citadel at the kingdom's peak. Reach the Citadel. ",
        "link": "https://hollowknight.wiki/w/Acts#Act_1:_Pharloom"
      },
      {
        "id": "threadspun-town",
        "label": "The Threadspun Town",
        "type": "quest",
        "flag": "The Threadspun Town",
        "icon": "assets/quest/Save_Quest_Icon.png",
        "description": "Break the silken curse ensnaring the town of Bellhart. Defeat Widow to free the town of Bellhart. ",
        "link": "https://hollowknight.wiki/w/Acts#Act_1:_Pharloom"
      },
      {
        "id": "grand-gate",
        "label": "Grand Gate",
        "type": "quest",
        "flag": "Grand Gate Bellshrines",
        "icon": "assets/quest/Gate_Quest_Icon.png",
        "description": "Awaken the old bells throughout the lands. Journey to the five Bellshrines throughout lower Pharloom and ring them to unlock the Grand Gate",
        "link": "https://hollowknight.wiki/w/Acts#Act_1:_Pharloom",
        "missable": true
      },
      {
        "id": "silent-halls",
        "label": "Silent Halls",
        "type": "quest",
        "flag": "Citadel Investigate",
        "icon": "assets/quest/Seek_Quest_Icon.png",
        "description": "Venture inside the Citadel and confront the veiled bugs. Confront Lace within the Choral Chambers.",
        "link": "https://hollowknight.wiki/w/Acts#Act_2:_Citadel_of_Song"
      },
      {
        "id": "pharlooms-crown-1",
        "label": "Pharloom’s Crown #1",
        "type": "quest",
        "flag": "Citadel Ascent",
        "icon": "assets/quest/Seek_Quest_Icon.png",
        "description": "Scale the Citadel and confront the one who haunts the lands of Pharloom. ",
        "link": "https://hollowknight.wiki/w/Acts#Act_2:_Citadel_of_Song"
      },
      {
        "id": "pharlooms-crown-2",
        "label": "Pharloom’s Crown #2",
        "type": "quest",
        "flag": "Citadel Ascent Melodies",
        "icon": "assets/quest/Seek_Quest_Icon.png",
        "description": "Learn the threefold melody and open the path to the Citadel’s crest.",
        "link": "https://hollowknight.wiki/w/Acts#Act_2:_Citadel_of_Song"
      },
      {
        "id": "pharlooms-crown-3",
        "label": "Pharloom’s Crown #3",
        "type": "quest",
        "flag": "Citadel Ascent Lift",
        "icon": "assets/quest/Seek_Quest_Icon.png",
        "description": "Rise above the Citadel and confront the one who haunts the land of Pharloom.",
        "link": "https://hollowknight.wiki/w/Acts#Act_2:_Citadel_of_Song"
      },
      {
        "id": "pale-monarch",
        "label": "Pale Monarch",
        "category": "Boss",
        "flag": "Silk Boss",
        "type": "journal",
        "subtype": "kills",
        "required": 1,
        "icon": "assets/quest/Seek_Quest_Icon.png",
        "description": "Confront the one who haunts the lands of Pharloom. Defeat Grand Mother Silk.",
        "link": "https://hollowknight.wiki/w/Acts#Act_2:_Citadel_of_Song"
      },
      {
        "id": "soul-snare",
        "label": "Soul Snare",
        "type": "quest",
        "flag": "Silk Defeat Snare",
        "icon": "assets/quest/Snare_Quest_Icon.png",
        "description": "Scale the Citadel and ensnare its monarch in a deadly trap. Defeat Grand Mother Silk with the Needolin.",
        "link": "https://hollowknight.wiki/w/Acts#Act_2:_Citadel_of_Song"
      },
      {
        "id": "after-the-fall",
        "label": "After the Fall",
        "type": "quest",
        "flag": "Black Thread Pt0",
        "icon": "assets/quest/Fall_Quest_Icon.png",
        "description": "Discover the fate of Pharloom. Escape the Cradle.",
        "link": "https://hollowknight.wiki/w/Acts#Act_3:_Abyss"
      },
      {
        "id": "awaiting-the-end",
        "label": "Awaiting the End",
        "type": "quest",
        "flag": "Black Thread Pt1 Shamans",
        "icon": "assets/quest/Fall_Quest_Icon.png",
        "description": "Confront the caretaker and his family in the Ruined Chapel beside Bone Bottom.",
        "link": "https://hollowknight.wiki/w/Acts#Act_3:_Abyss"
      },
      {
        "id": "beast-in-the-bells",
        "label": "Beast in the Bells",
        "type": "quest",
        "flag": "Bellbeast Rescue",
        "icon": "assets/quest/Beast_Quest_Icon.png",
        "description": "Descend into the Bellway and defeat the hostile creature within.",
        "link": "https://hollowknight.wiki/w/Acts#Act_3:_Abyss"
      },
      {
        "id": "the-dark-below-1",
        "label": "The Dark Below #1",
        "type": "quest",
        "flag": "Diving Bell Pt1 Inspect",
        "icon": "assets/quest/Fall_Quest_Icon.png",
        "description": "In Deep Docks, find a way to descend beneath Pharloom.",
        "link": "https://hollowknight.wiki/w/Acts#Act_3:_Abyss"
      },
      {
        "id": "the-dark-below-2",
        "label": "The Dark Below #2",
        "type": "quest",
        "flag": "Diving Bell Pt2 Ballow",
        "icon": "assets/quest/Fall_Quest_Icon.png",
        "description": "Find aid in the Deep Docks to access its diving bell and descend beneath Pharloom.",
        "link": "https://hollowknight.wiki/w/Acts#Act_3:_Abyss"
      },
      {
        "id": "the-dark-below-3",
        "label": "The Dark Below #3",
        "type": "quest",
        "flag": "Diving Bell Pt3 Descend",
        "icon": "assets/quest/Fall_Quest_Icon.png",
        "description": "Use the diving bell in Deep Docks to descend beneath Pharloom.",
        "link": "https://hollowknight.wiki/w/Acts#Act_3:_Abyss"
      },
      {
        "id": "the-dark-below-4",
        "label": "The Dark Below #4",
        "type": "quest",
        "flag": "Black Thread Pt2 Abyss",
        "icon": "assets/quest/Fall_Quest_Icon.png",
        "description": "Reach the source of the black threads within the Abyss.",
        "link": "https://hollowknight.wiki/w/Acts#Act_3:_Abyss"
      },
      {
        "id": "return-to-pharloom",
        "label": "Return to Pharloom",
        "type": "quest",
        "flag": "Black Thread Pt3 Escape",
        "icon": "assets/quest/Fall_Quest_Icon.png",
        "description": "Escape the Abyss.",
        "link": "https://hollowknight.wiki/w/Acts#Act_3:_Abyss"
      },
      {
        "id": "spell-seeker",
        "label": "Spell Seeker",
        "type": "quest",
        "flag": "Black Thread Pt4 Return",
        "icon": "assets/quest/Fall_Quest_Icon.png",
        "description": "Return to the Snail Shamans in the Ruined Chapel beside Bone Bottom.",
        "link": "https://hollowknight.wiki/w/Acts#Act_3:_Abyss"
      },
      {
        "id": "the-old-hearts",
        "label": "The Old Hearts",
        "type": "quest",
        "flag": "Black Thread Pt5 Heart",
        "icon": "assets/quest/Fall_Quest_Icon.png",
        "description": "Enliven and acquire the old hearts of Pharloom.",
        "link": "https://hollowknight.wiki/w/Acts#Act_3:_Abyss"
      },
      {
        "id": "last-dive",
        "label": "Last Dive",
        "category": "Boss",
        "flag": "Lost Lace",
        "type": "journal",
        "subtype": "kills",
        "required": 1,
        "icon": "assets/quest/Finale_Quest_Icon.png",
        "description": "Dive into the Void and cut Pharloom free.",
        "link": "https://hollowknight.wiki/w/Acts#Act_3:_Abyss"
      }
    ]
  },
  {
    "id": "wayfarer-quests",
    "label": "Wayfarer Wishes",
    "desc": "Wayfarer Wishes usually involve finding an item or NPC during Hornet's exploration of Pharloom at the request of another NPC. Later in the game, some Wayfarer Wishes will be placed that involve defeating optional bosses.",
    "contrib": 0,
    "items": [
      {
        "id": "lost-fleas-1",
        "label": "The Lost Fleas #1",
        "type": "quest",
        "flag": "Save the Fleas Pre",
        "icon": "assets/quest/wayfarer.png",
        "description": "Speak to the fleas before starting their rescue.",
        "link": "https://hollowknight.wiki/w/Category:Wishes#Wayfarer_Wishes"
      },
      {
        "id": "lost-fleas-2",
        "label": "The Lost Fleas #2",
        "type": "quest",
        "flag": "Save the Fleas",
        "icon": "assets/quest/wayfarer.png",
        "description": "Find and save the 5 lost fleas.",
        "link": "https://hollowknight.wiki/w/Category:Wishes#Wayfarer_Wishes"
      },
      {
        "id": "pinmasters-oil",
        "label": "Pinmaster's Oil",
        "type": "quest",
        "flag": "A Pinsmiths Tools",
        "icon": "assets/quest/wayfarer.png",
        "description": "Retrieve pale oil from the Citadel.",
        "link": "https://hollowknight.wiki/w/Category:Wishes#Wayfarer_Wishes",
        "missable": true
      },
      {
        "id": "my-missing-courier",
        "label": "My Missing Courier",
        "type": "quest",
        "flag": "Save Courier Short",
        "icon": "assets/quest/wayfarer.png",
        "description": "Search for traces of the courier Tipp and track his location.",
        "link": "https://hollowknight.wiki/w/Category:Wishes#Wayfarer_Wishes"
      },
      {
        "id": "my-missing-brother",
        "label": "My Missing Brother",
        "type": "quest",
        "flag": "Save Courier Tall",
        "icon": "assets/quest/wayfarer.png",
        "description": "Search for traces of the courier Pill and track his location.",
        "link": "https://hollowknight.wiki/w/Category:Wishes#Wayfarer_Wishes"
      },
      {
        "id": "balm-for-the-wounded",
        "label": "Balm for the Wounded",
        "type": "quest",
        "flag": "Save Sherma",
        "icon": "assets/quest/wayfarer.png",
        "description": "Search for traces of the pilgrim Sherma and track his location.",
        "link": "https://hollowknight.wiki/w/Category:Wishes#Wayfarer_Wishes"
      },
      {
        "id": "the-wandering-merchant",
        "label": "The Wandering Merchant",
        "type": "quest",
        "flag": "Save City Merchant",
        "icon": "assets/quest/wayfarer.png",
        "description": "Search for traces of the merchant Jubilana and track her location.",
        "link": "https://hollowknight.wiki/w/Category:Wishes#Wayfarer_Wishes"
      },
      {
        "id": "the-lost-merchant",
        "label": "The Lost Merchant",
        "type": "quest",
        "flag": "Save City Merchant Bridge",
        "icon": "assets/quest/wayfarer.png",
        "description": "Search for traces of the merchant Jubilana and track her location.",
        "link": "https://hollowknight.wiki/w/Category:Wishes#Wayfarer_Wishes"
      },
      {
        "id": "rite-of-rebirth",
        "label": "Rite of Rebirth",
        "type": "quest",
        "flag": "Wood Witch Curse",
        "icon": "assets/quest/wayfarer.png",
        "description": "Bind the twisted bud.",
        "link": "https://hollowknight.wiki/w/Category:Wishes#Wayfarer_Wishes"
      },
      {
        "id": "infestation-operation",
        "label": "Infestation Operation",
        "type": "quest",
        "flag": "Doctor Curse Cure",
        "icon": "assets/quest/wayfarer.png",
        "description": "Acquire steel spines from Crull and Benjin in Sinner's Road so Yarnaby can remove the parasite.",
        "link": "https://hollowknight.wiki/w/Category:Wishes#Wayfarer_Wishes"
      },
      {
        "id": "trails-end",
        "label": "Trail's End",
        "type": "quest",
        "flag": "Shakra Final Quest",
        "icon": "assets/quest/wayfarer.png",
        "description": "Search for Shakra and her master in Bilewater.",
        "link": "https://hollowknight.wiki/w/Category:Wishes#Wayfarer_Wishes"
      },
      {
        "id": "final-audience",
        "label": "Final Audience",
        "type": "quest",
        "flag": "Song Knight",
        "icon": "assets/quest/wayfarer.png",
        "description": "Track the second sentinel by their markers left near Songclave.",
        "link": "https://hollowknight.wiki/w/Category:Wishes#Wayfarer_Wishes"
      },
      {
        "id": "silk-and-soul-1",
        "label": "Silk and Soul #1",
        "type": "quest",
        "flag": "Soul Snare Pre",
        "icon": "assets/quest/wayfarer.png",
        "description": "Meet with the caretaker in Songclave.",
        "link": "https://hollowknight.wiki/w/Category:Wishes#Wayfarer_Wishes"
      },
      {
        "id": "silk-and-soul-2",
        "label": "Silk and Soul #2",
        "type": "quest",
        "flag": "Soul Snare",
        "icon": "assets/quest/wayfarer.png",
        "description": "Acquire the necessary components to build a powerful trap.",
        "link": "https://hollowknight.wiki/w/Category:Wishes#Wayfarer_Wishes"
      },
      {
        "id": "fatal-resolve-1",
        "label": "Fatal Resolve #1",
        "type": "quest",
        "flag": "Pinstress Battle Pre",
        "icon": "assets/quest/wayfarer.png",
        "description": "Travel to Pinstress's home at the far edge of the Blasted Steps and accept her challenge.",
        "link": "https://hollowknight.wiki/w/Category:Wishes#Wayfarer_Wishes"
      },
      {
        "id": "fatal-resolve-2",
        "label": "Fatal Resolve #2",
        "type": "quest",
        "flag": "Pinstress Battle",
        "icon": "assets/quest/wayfarer.png",
        "description": "Find Pinstress on the stormward side of Mount Fay and defeat her in battle.",
        "link": "https://hollowknight.wiki/w/Category:Wishes#Wayfarer_Wishes"
      },
      {
        "id": "pain-anguish-and-misery",
        "label": "Pain, Anguish and Misery",
        "type": "quest",
        "flag": "Tormented Trobbio",
        "icon": "assets/quest/wayfarer.png",
        "description": "Return to the Citadel's stage, beside the Whispering Vaults.",
        "link": "https://hollowknight.wiki/w/Category:Wishes#Wayfarer_Wishes"
      },
      {
        "id": "heros-call",
        "label": "Hero's Call",
        "type": "quest",
        "flag": "Garmond Black Threaded",
        "icon": "assets/quest/wayfarer.png",
        "description": "Seek out the distressed bug near the Blasted Steps Bellway.",
        "link": "https://hollowknight.wiki/w/Category:Wishes#Wayfarer_Wishes"
      },
      {
        "id": "ecstasy-of-the-end-1",
        "label": "Ecstasy of the End #1",
        "type": "quest",
        "flag": "Flea Games Pre",
        "icon": "assets/quest/wayfarer.png",
        "description": "Speak to Fleamaster Mooshka of Fleatopia.",
        "link": "https://hollowknight.wiki/w/Category:Wishes#Wayfarer_Wishes"
      },
      {
        "id": "ecstasy-of-the-end-2",
        "label": "Ecstasy of the End #2",
        "type": "quest",
        "flag": "Flea Games",
        "icon": "assets/quest/wayfarer.png",
        "description": "Achieve high score in the Flea Games and become Grand Champion.",
        "link": "https://hollowknight.wiki/w/Category:Wishes#Wayfarer_Wishes"
      }
    ]
  },
  {
    "id": "gather-wishes",
    "label": "Gather Wishes",
    "desc": "Gather Wishes involve exploring a region of the map (or in the case of the Great Taste of Pharloom wish, the entire map) and finding specific items to turn in to an NPC and complete the wish. Collecting the required items usually does not directly involve killing enemies, with some exceptions.",
    "contrib": 0,
    "items": [
      {
        "id": "berry-picking-1",
        "label": "Berry Picking #1",
        "type": "quest",
        "flag": "Mossberry Collection Pre",
        "icon": "assets/quest/Gather.png",
        "description": "Speak to the druid in Mosshome.",
        "link": "https://hollowknight.wiki/w/Category:Wishes#Gather_Wishes"
      },
      {
        "id": "berry-picking-2",
        "label": "Berry Picking #2",
        "type": "quest",
        "flag": "Mossberry Collection 1",
        "icon": "assets/quest/Gather.png",
        "description": "Collect 3 mossberries.",
        "link": "https://hollowknight.wiki/w/Category:Wishes#Gather_Wishes"
      },
      {
        "id": "rite-of-the-pollip",
        "label": "Rite of the Pollip",
        "type": "quest",
        "flag": "Shell Flowers",
        "icon": "assets/quest/Gather.png",
        "description": "Collect Pollip Hearts from the purple flowers of Shellwood.",
        "link": "https://hollowknight.wiki/w/Category:Wishes#Gather_Wishes"
      },
      {
        "id": "silver-bells",
        "label": "Silver Bells",
        "type": "quest",
        "flag": "Shiny Bell Goomba",
        "icon": "assets/quest/Gather.png",
        "description": "Collect silver bells in the Bellvein tunnels above and below Bellhart.",
        "link": "https://hollowknight.wiki/w/Category:Wishes#Gather_Wishes"
      },
      {
        "id": "alchemists-assistant",
        "label": "Alchemist's Assistant",
        "type": "quest",
        "flag": "Extractor Blue",
        "icon": "assets/quest/Gather.png",
        "description": "Collect 3 Plasmium Buds in the Lower Wormways.",
        "link": "https://hollowknight.wiki/w/Category:Wishes#Gather_Wishes"
      },
      {
        "id": "great-taste-of-pharloom",
        "label": "Great Taste of Pharloom",
        "type": "quest",
        "flag": "Great Gourmand",
        "icon": "assets/quest/Gather.png",
        "description": "Collect rare delicacies of Pharloom.",
        "link": "https://hollowknight.wiki/w/Category:Wishes#Gather_Wishes"
      },
      {
        "id": "advanced-alchemy",
        "label": "Advanced Alchemy",
        "type": "quest",
        "flag": "Extractor Blue Worms",
        "icon": "assets/quest/Gather.png",
        "description": "Collect Plasmified Blood from infected creatures in the Wormways",
        "link": "https://hollowknight.wiki/w/Category:Wishes#Gather_Wishes"
      }
    ]
  },
  {
    "id": "hunt-wishes",
    "label": "Hunt Wishes",
    "desc": "Hunt Wishes involve killing normal (or occasionally special) enemies in a specific part of the world and collecting items dropped by them to turn in and complete the wish. The only exception to this is the Dark Hearts wish, which does not require Hornet to collect any items and whose enemy is found all across Pharloom. ",
    "contrib": 0,
    "items": [
      {
        "id": "garb-of-the-pilgrims",
        "label": "Garb of the Pilgrims",
        "type": "quest",
        "flag": "Pilgrim Rags",
        "icon": "assets/quest/Hunt_Wishes.png",
        "description": "Hunt haunted pilgrims of Pharloom and collect pilgrim shawls from their bodies.",
        "link": "https://hollowknight.wiki/w/Category:Wishes#Hunt_Wishes",
        "missable": true
      },
      {
        "id": "flexile-spines",
        "label": "Flexile Spines",
        "type": "quest",
        "flag": "Brolly Get",
        "icon": "assets/quest/Hunt_Wishes.png",
        "description": "Hunt Hokers in the far fields and collect spine cores.",
        "link": "https://hollowknight.wiki/w/Category:Wishes#Hunt_Wishes"
      },
      {
        "id": "volatile-flintbeetles",
        "label": "Volatile Flintbeetles",
        "type": "quest",
        "flag": "Rock Rollers",
        "icon": "assets/quest/Hunt_Wishes.png",
        "description": "Track down Flintbeetles in the Marrow and defeat them to collect flintgems. Flintbeetles can be tracked by their stone-sheddings and aromatic dung.",
        "link": "https://hollowknight.wiki/w/Category:Wishes#Hunt_Wishes",
        "missable": true
      },
      {
        "id": "crawbug-clearing-pre",
        "label": "Crawbug Clearing #1",
        "type": "quest",
        "flag": "Crow Feathers Pre",
        "icon": "assets/quest/Hunt_Wishes.png",
        "description": "Speak to Creige of the Halfway Home in Greymoor.",
        "link": "https://hollowknight.wiki/w/Category:Wishes#Hunt_Wishes"
      },
      {
        "id": "crawbug-clearing",
        "label": "Crawbug Clearing #2",
        "type": "quest",
        "flag": "Crow Feathers",
        "icon": "assets/quest/Hunt_Wishes.png",
        "description": "Hunt Crawbugs in Greymoor and collect their ragpelt.",
        "link": "https://hollowknight.wiki/w/Category:Wishes#Hunt_Wishes"
      },
      {
        "id": "roach-guts",
        "label": "Roach Guts",
        "type": "quest",
        "flag": "Roach Killing",
        "icon": "assets/quest/Hunt_Wishes.png",
        "description": "Hunt the Muckroaches of Sinner's Road and collect roach guts from their bodies.",
        "link": "https://hollowknight.wiki/w/Category:Wishes#Hunt_Wishes",
        "missable": true
      },
      {
        "id": "fine-pins",
        "label": "Fine Pins",
        "type": "quest",
        "flag": "Fine Pins",
        "icon": "assets/quest/Hunt_Wishes.png",
        "description": "Hunt pin-welding Choirbugs of the Citadel and collect fine pins.",
        "link": "https://hollowknight.wiki/w/Category:Wishes#Hunt_Wishes"
      },
      {
        "id": "cloaks-of-the-choir",
        "label": "Cloaks of the Choir",
        "type": "quest",
        "flag": "Song Pilgrim Cloaks",
        "icon": "assets/quest/Hunt_Wishes.png",
        "description": "Hunt cloaked Choirbugs of the Citadel and collect choir cloaks from their bodies.",
        "link": "https://hollowknight.wiki/w/Category:Wishes#Hunt_Wishes"
      },
      {
        "id": "broodfeast",
        "label": "Broodfeast",
        "type": "quest",
        "flag": "Huntress Quest",
        "icon": "assets/quest/Hunt_Wishes.png",
        "description": "Use tools to acquire organs of various types so Huntress may feed her brood.",
        "link": "https://hollowknight.wiki/w/Category:Wishes#Hunt_Wishes"
      },
      {
        "id": "runtfeast",
        "label": "Runtfeast",
        "type": "quest",
        "flag": "Huntress Quest Runt",
        "icon": "assets/quest/Hunt_Wishes.png",
        "description": "Use tools to acquire organs of various types so Runt may feed.",
        "link": "https://hollowknight.wiki/w/Category:Wishes#Hunt_Wishes"
      },
      {
        "id": "dark-hearts",
        "label": "Dark Hearts",
        "type": "quest",
        "flag": "Destroy Thread Cores",
        "icon": "assets/quest/Hunt_Wishes.png",
        "description": "Destroy void masses throughout Pharloom.",
        "link": "https://hollowknight.wiki/w/Category:Wishes#Hunt_Wishes"
      }
    ]
  },
  {
    "id": "grand_hunt-wishes",
    "label": "Grand Hunt Wishes",
    "desc": "Grand Hunt Wishes are always accepted from a Wishwall, and involve finding and killing a unique boss enemy and claiming a trophy item from them to turn in and complete the wish. They carry a high reward, either yielding a Heavy Rosary Necklace or a Mask Shard.",
    "contrib": 0,
    "items": [
      {
        "id": "the-terrible-tyrant",
        "label": "The Terrible Tyrant",
        "type": "quest",
        "flag": "Skull King",
        "icon": "assets/quest/Grand_Hunt_Quest_Icon.png",
        "description": "Hunt a Skull Tyrant of the Marrow.",
        "link": "https://hollowknight.wiki/w/Category:Wishes#Grand_Hunt_Wishes",
        "missable": true
      },
      {
        "id": "savage-beastfly",
        "label": "Savage Beastfly",
        "type": "quest",
        "flag": "Beastfly Hunt",
        "icon": "assets/quest/Grand_Hunt_Quest_Icon.png",
        "description": "Track down the savage Beastfly in the Far Fields and defeat it.",
        "link": "https://hollowknight.wiki/w/Category:Wishes#Grand_Hunt_Wishes"
      },
      {
        "id": "the-wailing-mother",
        "label": "The Wailing Mother",
        "type": "quest",
        "flag": "Broodmother Hunt",
        "icon": "assets/quest/Grand_Hunt_Quest_Icon.png",
        "description": "Track down the wailing creature in the Slab and slay it.",
        "link": "https://hollowknight.wiki/w/Category:Wishes#Grand_Hunt_Wishes"
      },
      {
        "id": "the-hidden-hunter",
        "label": "The Hidden Hunter",
        "type": "quest",
        "flag": "Ant Trapper",
        "icon": "assets/quest/Grand_Hunt_Quest_Icon.png",
        "description": "Track the one who stole Gilly's keepsake near the Bellshrine between Deep Docks and Far Fields.",
        "link": "https://hollowknight.wiki/w/Category:Wishes#Grand_Hunt_Wishes"
      }
    ]
  },
  {
    "id": "donate-wishes",
    "label": "Donate Wishes",
    "desc": "Contribute shell shards and rosaries to support rebuilding efforts across Pharloom.",
    "contrib": 0,
    "items": [
      {
        "id": "bone-bottom-repairs",
        "label": "Bone Bottom Repairs",
        "type": "quest",
        "flag": "Building Materials",
        "icon": "assets/quest/donate.png",
        "description": "Donate 200 shell shards.",
        "link": "https://hollowknight.wiki/w/Category:Wishes#Donate_Wishes"
      },
      {
        "id": "a-lifesaving-bridge",
        "label": "A Lifesaving Bridge",
        "type": "quest",
        "flag": "Building Materials (Bridge)",
        "icon": "assets/quest/donate.png",
        "description": "Donate 300 shell shards to aid the building of a bridge.",
        "link": "https://hollowknight.wiki/w/Category:Wishes#Donate_Wishes"
      },
      {
        "id": "restoration-of-bellhart",
        "label": "Restoration of Bellhart",
        "type": "quest",
        "flag": "Belltown House Start",
        "icon": "assets/quest/donate.png",
        "description": "Donate 250 rosaries to aid the rebuilding of Bellhart.",
        "link": "https://hollowknight.wiki/w/Category:Wishes#Donate_Wishes"
      },
      {
        "id": "an-icon-of-hope",
        "label": "An Icon of Hope",
        "type": "quest",
        "flag": "Building Materials (Statue)",
        "icon": "assets/quest/donate.png",
        "description": "Donate 400 shell shards to aid the construction of an icon of hope.",
        "link": "https://hollowknight.wiki/w/Category:Wishes#Donate_Wishes",
        "missable": true
      },
      {
        "id": "bellharts-glory",
        "label": "Bellhart's Glory",
        "type": "quest",
        "flag": "Belltown House Mid",
        "icon": "assets/quest/donate.png",
        "description": "Donate 400 rosaries to complete the rebuilding of Bellhart.",
        "link": "https://hollowknight.wiki/w/Category:Wishes#Donate_Wishes"
      },
      {
        "id": "building-up-songclave",
        "label": "Building Up Songclave",
        "type": "quest",
        "flag": "Songclave Donation 1",
        "icon": "assets/quest/donate.png",
        "description": "Donate 300 rosaries to aid the growing Songclave.",
        "link": "https://hollowknight.wiki/w/Category:Wishes#Donate_Wishes"
      },
      {
        "id": "strengthening-songclave",
        "label": "Strengthening Songclave",
        "type": "quest",
        "flag": "Songclave Donation 2",
        "icon": "assets/quest/donate.png",
        "description": "Donate rosaries to aid the Songclave's residents.",
        "link": "https://hollowknight.wiki/w/Category:Wishes#Donate_Wishes"
      }
    ]
  },
  {
    "id": "delivery-wishes",
    "label": "Delivery Wishes",
    "desc": "Deliver rare and precious items to recipients across Pharloom.",
    "contrib": 0,
    "items": [
      {
        "id": "queens-egg",
        "label": "Queen's Egg",
        "type": "quest",
        "flag": "Courier Delivery Dustpens Slave",
        "icon": "assets/quest/Delivery.png",
        "description": "Deliver the Queen's Egg to Styx of Sinner's Road.",
        "link": "https://hollowknight.wiki/w/Category:Wishes#Delivery_Wishes",
        "mode": "normal",
        "act": 1
      },
      {
        "id": "delivery-bonebottom",
        "label": "Bone Bottom Supplies",
        "type": "quest",
        "flag": "Courier Delivery Bonebottom",
        "icon": "assets/quest/Delivery.png",
        "description": "Deliver supplies to the fixer Flick in Bone Bottom.",
        "link": "https://hollowknight.wiki/w/Category:Wishes#Delivery_Wishes",
        "mode": "normal",
        "act": 1,
        "missable": true
      },
      {
        "id": "delivery-pilgrim-rest",
        "label": "Pilgrim's Rest Supplies",
        "type": "quest",
        "flag": "Courier Delivery Pilgrims Rest",
        "icon": "assets/quest/Delivery.png",
        "description": "Deliver supplies to Mort in Pilgrim's Rest.",
        "link": "https://hollowknight.wiki/w/Category:Wishes#Delivery_Wishes",
        "mode": "normal",
        "act": 1,
        "missable": true
      },
      {
        "id": "delivery-songclade-supplies",
        "label": "Songclave Supplies",
        "type": "quest",
        "flag": "Courier Delivery Songclave",
        "icon": "assets/quest/Delivery.png",
        "description": "Deliver supplies to the Caretaker in Songclave.",
        "link": "https://hollowknight.wiki/w/Category:Wishes#Delivery_Wishes",
        "mode": "normal",
        "act": 2
      },
      {
        "id": "delivery-songclade-supplies",
        "label": "Fleatopia Supplies",
        "type": "quest",
        "flag": "Courier Delivery Fleatopia",
        "icon": "assets/quest/Delivery.png",
        "description": "Deliver supplies to the Fleamaster Mooshka in Fleatopia.",
        "link": "https://hollowknight.wiki/w/Category:Wishes#Delivery_Wishes",
        "mode": "normal",
        "act": 2
      },
      {
        "id": "liquid-lacquer",
        "label": "Liquid Lacquer",
        "type": "quest",
        "flag": "Courier Delivery Mask Maker",
        "icon": "assets/quest/Delivery.png",
        "description": "Deliver liquid lacquer to the Mask Maker upon Mount Fay.",
        "link": "https://hollowknight.wiki/w/Category:Wishes#Delivery_Wishes",
        "act": 2
      },
      {
        "id": "survivor-supplies",
        "label": "Survivor's Camp Supplies",
        "type": "quest",
        "flag": "Courier Delivery Fixer",
        "icon": "assets/quest/Delivery.png",
        "description": "Deliver supplies to Flick at the Survivor's Camp.",
        "link": "https://hollowknight.wiki/w/Category:Wishes#Delivery_Wishes",
        "act": 3
      }
    ]
  },
  {
    "id": "unique-wishes",
    "label": "Unique Wishes",
    "desc": "Rare and singular wishes tied to special figures and events across Pharloom.",
    "contrib": 0,
    "items": [
      {
        "id": "bugs-of-pharloom",
        "label": "Bugs of Pharloom",
        "type": "quest",
        "flag": "Journal",
        "icon": "assets/quest/Learn_Quest_Icon.png",
        "description": "Defeat the many creatures of Pharloom and fill out the Hunter's Journal.",
        "link": "https://hollowknight.wiki/w/Category:Wishes#Unique_Wishes"
      },
      {
        "id": "fastest-in-pharloom-1",
        "label": "Fastest in Pharloom #1",
        "type": "quest",
        "flag": "Sprintmaster Pre",
        "icon": "assets/quest/Sprint_Quest_Icon.png",
        "description": "Meet with the Sprintmaster Swift at the furthest border of the Far Fields.",
        "link": "https://hollowknight.wiki/w/Category:Wishes#Unique_Wishes"
      },
      {
        "id": "fastest-in-pharloom-2",
        "label": "Fastest in Pharloom #2",
        "type": "quest",
        "flag": "Sprintmaster Race",
        "icon": "assets/quest/Sprint_Quest_Icon.png",
        "description": "Race Sprintmaster Swift to discover Pharloom's fastest bug.",
        "link": "https://hollowknight.wiki/w/Category:Wishes#Unique_Wishes"
      },
      {
        "id": "passing-of-the-age",
        "label": "Passing of the Age",
        "type": "quest",
        "flag": "Mr Mushroom",
        "icon": "assets/quest/Witness_Quest_Icon.png",
        "description": "We speak the wish of the Master Herald, he who signs an Age's end.",
        "link": "https://hollowknight.wiki/w/Category:Wishes#Unique_Wishes"
      },
      {
        "id": "a_vassal_lost",
        "label": "A Vassal Lost",
        "type": "quest",
        "flag": "Steel Sentinel",
        "icon": "assets/quest/Steel_Wish_Art.png",
        "description": "Investigate the resting sites marked by Steel Seer Zi to uncover the location of her vassal.",
        "link": "https://hollowknight.wiki/w/Category:Wishes#Unique_Wishes",
        "mode": "steel"
      }
    ]
  }
]
